jman/__init__.py
jman/client.py
jman/current_job.py
jman/job.py
jman/manager.py
jman/mod_func_loader.py
jman/server.py
jman/serverd.py
jman-0.1.2.dist-info/LICENSE
jman-0.1.2.dist-info/METADATA
jman-0.1.2.dist-info/WHEEL
jman-0.1.2.dist-info/entry_points.txt
jman-0.1.2.dist-info/top_level.txt
jman-0.1.2.dist-info/RECORD
