Metadata-Version: 2.1
Name: jman
Version: 0.1.2
Summary: Job manager with queryable server.
Home-page: https://github.com/tgree/jman
Author: Terry Greeniaus
Author-email: terrygreeniaus@gmail.com
License: License :: OSI Approved :: MIT License
Keywords: jman job management
Platform: UNKNOWN
Classifier: Operating System :: POSIX
Classifier: Programming Language :: Python :: 3
Classifier: License :: OSI Approved :: MIT License
Requires-Python: >=3.6
Requires-Dist: pyreap (>=0.9.1)
Requires-Dist: requests
